FlcatBrowser/__init__.py
FlcatBrowser/actions.c
FlcatBrowser/actions.cp39-win32.pyd
FlcatBrowser/actions.pyi
FlcatBrowser/browser.py
FlcatBrowser/browser_task_queue.py
FlcatBrowser/enum.py
FlcatBrowser/exception.py
FlcatBrowser/version.py
FlcatBrowser/website.py
FlcatBrowser/_js/__init__.py
FlcatBrowser/_js/base_request.js
FlcatBrowser/_js/base_requests.c
FlcatBrowser/_js/base_requests.cp39-win32.pyd
FlcatBrowser/_js/base_requests.pyi
FlcatBrowser/plugin/intercept.py
FlcatBrowser/utils/__init__.py
FlcatBrowser/utils/browser.py
FlcatBrowser/utils/clipboard.c
FlcatBrowser/utils/clipboard.cp39-win32.pyd
FlcatBrowser/utils/clipboard.pyi
FlcatBrowser/utils/common.py
FlcatBrowser/utils/cross_platform.py
FlcatBrowser/utils/file_downloader.py
FlcatBrowser/utils/id.py
FlcatBrowser/utils/port.py
FlcatBrowser/utils/response.py
FlcatBrowser/utils/task_queue.py
FlcatBrowser/utils/url.py
FlcatBrowser/utils/FingerPrint/_ua.py
FlcatBrowser/utils/FingerPrint/device_info.c
FlcatBrowser/utils/FingerPrint/device_info.cp39-win32.pyd
FlcatBrowser/utils/FingerPrint/device_info.pyi
FlcatBrowser/utils/FingerPrint/finger_print.c
FlcatBrowser/utils/FingerPrint/finger_print.cp39-win32.pyd
FlcatBrowser/utils/FingerPrint/finger_print.pyi
FlcatBrowser/utils/FingerPrint/ua.c
FlcatBrowser/utils/FingerPrint/ua.cp39-win32.pyd
FlcatBrowser/utils/FingerPrint/ua.pyi
flcatbrowser-0.1.86.dist-info/METADATA
flcatbrowser-0.1.86.dist-info/WHEEL
flcatbrowser-0.1.86.dist-info/top_level.txt
flcatbrowser-0.1.86.dist-info/RECORD
