Metadata-Version: 2.4
Name: FlcatBrowser
Version: 0.1.86
Summary: flcat browser
Author-email: yhhit <827077539@qq.com>
Project-URL: Homepage, https://github.com/yhhit/FlcatBrowser
Requires-Python: >=3.9
Requires-Dist: FlcatDrissionPage>=0.1.33
